basic_auth/__init__.py
basic_auth/basic_auth.py
tests/__init__.py
tests/test_basic.py
tests/test_general.py
tests/test_wso.py
tests/test_ztidy_up.py
basic_auth-0.0.2.dist-info/LICENSE
basic_auth-0.0.2.dist-info/METADATA
basic_auth-0.0.2.dist-info/WHEEL
basic_auth-0.0.2.dist-info/top_level.txt
basic_auth-0.0.2.dist-info/RECORD
