Metadata-Version: 2.1
Name: basic-auth
Version: 0.0.2
Summary: A package for read and writing auth
Home-page: https://github.com/rorymurdock/basic_auth
Author: Rory Murdock
Author-email: rory@itmatic.com.au
License: UNKNOWN
Platform: UNKNOWN
Classifier: Development Status :: 4 - Beta
Classifier: License :: OSI Approved :: Apache Software License
Classifier: Operating System :: OS Independent
